Metadata-Version: 2.1
Name: chrome-for-testing-manager
Version: 1.0.1
Summary: Automatic download and manage Chrome and Chromedriver, and ensures that their versions match
Home-page: https://github.com/sukaiyi/chrome-for-testing-manager-python
Author: sukaiyi
Author-email: im.sukaiyi@gmail.com
License: Apache license 2.0
Platform: all
Classifier: Intended Audience :: Developers
Classifier: Operating System :: OS Independent
Classifier: Natural Language :: Chinese (Simplified)
Classifier: Programming Language :: Python
Classifier: Programming Language :: Python :: 3
Classifier: Programming Language :: Python :: 3.5
Classifier: Programming Language :: Python :: 3.6
Classifier: Programming Language :: Python :: 3.7
Classifier: Programming Language :: Python :: 3.8
Classifier: Topic :: Software Development :: Libraries
License-File: LICENSE
Requires-Dist: requests>=2.0.1
